adc/__init__.py
adc/auth.py
adc/consumer.py
adc/errors.py
adc/io.py
adc/kafka.py
adc/oidc.py
adc/producer.py
adc_streaming-2.5.0.dist-info/LICENSE
adc_streaming-2.5.0.dist-info/METADATA
adc_streaming-2.5.0.dist-info/WHEEL
adc_streaming-2.5.0.dist-info/top_level.txt
adc_streaming-2.5.0.dist-info/RECORD
