Metadata-Version: 2.1
Name: adc-streaming
Version: 2.5.0
Summary: Astronomy Data Commons streaming client libraries
Home-page: https://github.com/astronomy-commons/adc-streaming
Author: Astronomy Data Commons Team
Author-email: swnelson@uw.edu
License: BSD
Classifier: Programming Language :: Python :: 3
Classifier: License :: OSI Approved :: BSD License
Classifier: Development Status :: 3 - Alpha
Classifier: Operating System :: POSIX :: Linux
Classifier: Operating System :: MacOS :: MacOS X
License-File: LICENSE
Requires-Dist: authlib
Requires-Dist: confluent-kafka (!=2.1.0,!=2.1.1,>=1.6.1)
Requires-Dist: requests
Requires-Dist: tqdm
Requires-Dist: certifi (>=2020.04.05.1)
Requires-Dist: dataclasses ; python_version < "3.7"
Requires-Dist: importlib-metadata ; python_version < "3.8"
Requires-Dist: typing-extensions ; python_version < "3.8"
Provides-Extra: dev
Requires-Dist: autopep8 ; extra == 'dev'
Requires-Dist: docker ; extra == 'dev'
Requires-Dist: flake8 ; extra == 'dev'
Requires-Dist: isort ; extra == 'dev'
Requires-Dist: pytest ; extra == 'dev'
Requires-Dist: pytest-timeout ; extra == 'dev'
Requires-Dist: pytest-integration ; extra == 'dev'
Requires-Dist: sphinx ; extra == 'dev'
Requires-Dist: sphinx-rtd-theme ; extra == 'dev'
Requires-Dist: twine ; extra == 'dev'
